hanlperceptron/__init__.py
hanlperceptron/analyzer.py
hanlperceptron/feature.py
hanlperceptron/instance.py
hanlperceptron/model.py
hanlperceptron/other.py
hanlperceptron/utils.py
hanlperceptron/data/CharTable.txt
hanlperceptron/data/CoreNatureDictionary.txt
hanlperceptron-0.2.0.dist-info/LICENSE
hanlperceptron-0.2.0.dist-info/METADATA
hanlperceptron-0.2.0.dist-info/WHEEL
hanlperceptron-0.2.0.dist-info/top_level.txt
hanlperceptron-0.2.0.dist-info/RECORD
