Metadata-Version: 2.1
Name: hanlperceptron
Version: 0.2.0
Summary: Native Python HanLP Perceptron Model: HanLPerceptron
Home-page: https://github.com/fann1993814/HanLPerceptron
Author: Jason Fan
Author-email: fann1993814@gmail.com
License: Apache License 2.0
Keywords: corpus,machine-learning,NLU,NLP
Platform: UNKNOWN
Classifier: Intended Audience :: Developers
Classifier: Natural Language :: Chinese (Simplified)
Classifier: Natural Language :: Chinese (Traditional)
Classifier: Operating System :: OS Independent
Classifier: Programming Language :: Python
Classifier: Programming Language :: Python :: 3
Classifier: Topic :: Text Processing
Classifier: Topic :: Text Processing :: Indexing
Classifier: Topic :: Text Processing :: Linguistic
Requires-Python: >=3.6
Requires-Dist: numpy (>=1.15)
Requires-Dist: joblib (>=0.14.0)
